pgdict/__init__.py
pgdict/exceptions.py
pgdict/pgdict.py
pgdict-0.0.3.dist-info/LICENSE
pgdict-0.0.3.dist-info/METADATA
pgdict-0.0.3.dist-info/WHEEL
pgdict-0.0.3.dist-info/top_level.txt
pgdict-0.0.3.dist-info/RECORD
