Metadata-Version: 2.1
Name: pgdict
Version: 0.0.3
Summary: UNKNOWN
Home-page: UNKNOWN
License: MIT
Platform: UNKNOWN
Classifier: Programming Language :: Python :: 3.8
Requires-Python: >=3.8
Requires-Dist: psycopg2-binary (==2.9.5)
